Workbook

Sheet Read Me
A1: Website Project Master Task Library — India (small two-person studio)
A2: Version | B2: v1.0 · 28 Sep 2026 · default values, not absolute truths
A4: What this is | B4: A task library covering the full lifecycle from lead to maintenance. Delete rows that do not apply to a project; never delete MUST HAVE rows without a written reason.
A5: Classification tags | B5: [MUST HAVE] needed on every project of this type · [RECOMMENDED] strong best practice · [OPTIONAL] nice to have · [CONDITIONAL] only if the feature/situation exists · [POST-LAUNCH] after go-live / under maintenance
A6: Legal vs practice | B6: A [MUST HAVE] tag means the task is operationally essential, not that a law requires it. Legal requirements are discussed separately in the master document with sources.
A7: Default points | B7: Points ≈ midpoint of typical effort (hours) × complexity factor (Low 1.0, Medium 1.25, High 1.5), rounded; minimum 1. Per-page/per-item tasks show points per unit. 'Varies' effort tasks default to 1 and should be sized at planning.
A8: Customising points | B8: 1) Lock points at kickoff (J-08). 2) Change defaults only in quarterly calibration (BO-02), forward-looking only. 3) Per-project overrides need both partners' approval and a reason. 4) For per-unit tasks multiply by quantity (pages, products, templates).
A9: Billable column | B9: 'No — included' = part of the standard price. 'Yes — separate' = quote as an add-on. 'Conditional' = depends on what the proposal includes.
A10: Owner roles | B10: Sales, PM, Design, Content, FE (frontend), BE (backend), DevOps, QA, Either. In a two-person studio each partner covers several roles; the role says what kind of work it is, which helps calibrate points.
A11: Sheets | B11: Task Library (all 22 fields) · Contribution Library (Part 13 columns) · Category Summary (live formulas)

Sheet Task Library
A1: ID | B1: Category code | C1: Category | D1: Task | E1: Description | F1: Why necessary | G1: When | H1: Prerequisites / dependencies | I1: Typical owner | J1: Deliverable / output | K1: Evidence of completion | L1: Client approval? | M1: Classification | N1: Complexity | O1: Typical effort | P1: Default points | Q1: Possible risks | R1: Common mistakes | S1: If skipped | T1: In standard project? | U1: Separate billable item? | V1: Post-launch maintenance?
A2: A-01 | B2: A | C2: Lead Generation | D2: Build prospect list | E2: List local businesses in a target niche/area with no site, an outdated site, or a site that fails mobile/speed checks; record name, contact, source, current URL | F2: A pipeline of qualified leads is the only reliable source of projects | G2: Business-level, ongoing | H2: Ideal client profile agreed | I2: Sales | J2: Prospect sheet rows | K2: CRM/sheet export with dates | L2: No | M2: [RECOMMENDED] | N2: Low | O2: 1–3 h per 20 leads | P2: 2 | Q2: Scraping personal data without basis; wasted time on poor-fit niches | R2: Listing everyone instead of a niche; no source tracking | S2: Irregular, referral-only income | T2: No | U2: No — included in base price | V2: No
A3: A-02 | B3: A | C3: Lead Generation | D3: Prospect mini-audit | E3: Quick audit of prospect's site, Google Business Profile, socials: mobile view, speed, HTTPS, broken contact info; 3–5 concrete findings | F3: Gives a specific, credible reason to talk | G3: Pre-sales | H3: A-01 | I3: Sales | J3: 1-page audit or screenshot set | K3: Audit doc/screenshots linked to lead | L3: No | M3: [OPTIONAL] | N3: Low | O3: 0.5–1 h | P3: 1 | Q3: Over-investing in leads that never reply | R3: Generic audits; insulting tone | S3: Weak, generic pitch | T3: No | U3: No — included in base price | V3: No
A4: A-03 | B4: A | C4: Lead Generation | D4: Log lead with source and status | E4: Create lead record: business, contact person, phone/email, source, date, next action, status | F4: Lead source data shows which channels pay off; prevents double contact | G4: Pre-sales | H4: None | I4: Either | J4: Lead record | K4: CRM/app entry with timestamp | L4: No | M4: [MUST HAVE] | N4: Low | O4: 5–10 min | P4: 1 | Q4: Lost follow-ups | R4: Keeping leads only in personal WhatsApp | S4: Partners contact same lead twice; lost revenue | T4: Yes | U4: No — included in base price | V4: No
A5: A-04 | B5: A | C5: Lead Generation | D5: Referral and partner outreach | E5: Ask past clients, CAs, printers, photographers, marketers for referrals; track referrer | F5: Referrals convert better and cost less | G5: Business-level, ongoing | H5: At least one delivered project | I5: Sales | J5: Referral log | K5: Messages/call notes | L5: No | M5: [RECOMMENDED] | N5: Low | O5: 1–2 h/month | P5: 2 | Q5: Promising referral fees without records | R5: No referral tracking | S5: Slower growth | T5: No | U5: No — included in base price | V5: No
A6: B-01 | B6: B | C6: Client Outreach | D6: Write personalised outreach message | E6: Draft first message referencing audit findings and a clear next step (15-min call) | F6: Personalised, specific outreach gets replies; generic spam damages reputation | G6: Pre-sales | H6: A-02, A-03 | I6: Sales | J6: Message draft | K6: Sent message copy/screenshot | L6: No | M6: [RECOMMENDED] | N6: Low | O6: 15–30 min | P6: 1 | Q6: Spam complaints; WhatsApp account restriction for bulk messaging | R6: Copy-paste bulk messages; no call to action | S6: Low reply rate | T6: No | U6: No — included in base price | V6: No
A7: B-02 | B7: B | C7: Client Outreach | D7: First contact and log outcome | E7: Call/visit/message; record date, channel, who, outcome, next step | F7: Creates the audit trail for who sourced the client | G7: Pre-sales | H7: B-01 | I7: Sales | J7: Contact log entry | K7: Call log/meeting note | L7: No | M7: [MUST HAVE] | N7: Low | O7: 10–30 min | P7: 1 | Q7: Disputes between partners about who brought the client | R7: Not logging verbal conversations | S7: Unclear lead credit; forgotten promises | T7: Yes | U7: No — included in base price | V7: No
A8: B-03 | B8: B | C8: Client Outreach | D8: Follow-up sequence | E8: Up to 2–3 spaced follow-ups with added value (example, audit point); stop after no response | F8: Most deals need follow-up; a cap prevents harassment | G8: Pre-sales | H8: B-02 | I8: Sales | J8: Follow-up entries | K8: Message copies with dates | L8: No | M8: [RECOMMENDED] | N8: Low | O8: 10 min each | P8: 1 | Q8: Annoying prospects | R8: Endless follow-ups; no stop rule | S8: Lost warm leads | T8: No | U8: No — included in base price | V8: No
A9: B-04 | B9: B | C9: Client Outreach | D9: Share portfolio and case studies | E9: Send 2–3 relevant samples with outcome, scope and price band | F9: Proof reduces perceived risk | G9: Pre-sales | H9: B-02 | I9: Sales | J9: Portfolio link/PDF | K9: Sent link record | L9: No | M9: [RECOMMENDED] | N9: Low | O9: 15–30 min | P9: 1 | Q9: Showing client work without permission | R9: Showing unrelated work; outdated links | S9: Harder to close | T9: No | U9: No — included in base price | V9: No
A10: C-01 | B10: C | C10: Sales | D10: Qualification call | E10: 15–30 min call covering need, decision-maker, budget range, timeline, existing assets | F10: Filters out bad-fit and non-paying clients early | G10: Pre-sales | H10: B-02 | I10: Sales | J10: Qualification notes | K10: Call note in app | L10: No | M10: [MUST HAVE] | N10: Low | O10: 0.5–1 h | P10: 1 | Q10: Talking to someone without authority | R10: Skipping budget question; promising features on call | S10: Wasted discovery and proposal time | T10: Yes | U10: No — included in base price | V10: No
A11: C-02 | B11: C | C11: Sales | D11: Go/no-go decision | E11: Decide proceed or decline using checklist: budget fit, timeline realism, legal business, red flags; record reason | F11: Protects capacity and cashflow | G11: Pre-sales | H11: C-01 | I11: Either | J11: Decision record | K11: Decision entry with reason | L11: No | M11: [RECOMMENDED] | N11: Low | O11: 10–20 min | P11: 1 | Q11: Taking every project, including toxic ones | R11: No written reason | S11: Scope/payment disputes later | T11: Yes | U11: No — included in base price | V11: No
A12: C-03 | B12: C | C12: Sales | D12: Sales meeting or demo | E12: Present approach, process, timeline, samples; explain payment terms and ownership model upfront | F12: Sets expectations before numbers are discussed | G12: Pre-sales | H12: C-02 | I12: Sales | J12: Meeting notes | K12: Meeting record + attendee list | L12: No | M12: [RECOMMENDED] | N12: Medium | O12: 1–2 h incl. prep | P12: 2 | Q12: Over-promising | R12: Not explaining client responsibilities | S12: Mismatched expectations | T12: Yes | U12: No — included in base price | V12: No
A13: C-04 | B13: C | C13: Sales | D13: Pricing negotiation | E13: Negotiate by adjusting scope, not just price; record every concession in writing | F13: Discounts without scope change erode margin | G13: Pre-sales | H13: G-03 | I13: Sales | J13: Negotiation notes, revised proposal | K13: Email/notes, version history | L13: Yes | M13: [RECOMMENDED] | N13: Medium | O13: 0.5–2 h | P13: 2 | Q13: Verbal concessions later disputed | R13: Cutting price but keeping scope | S13: Unprofitable project | T13: Cond | U13: No — included in base price | V13: No
... A344: BO-02 | B344: BO | C344: Partner Governance (added) | D344: Points calibration review | E344: Quarterly compare points vs actual effort across projects; adjust defaults going forward only | F344: Keeps defaults realistic | G344: Business-level, quarterly | H344: BJ-01 | I344: Either (both) | J344: Updated defaults | K344: Changelog of defaults | L344: No | M344: [RECOMMENDED] | N344: Low | O344: 1–2 h | P344: 1 | Q344: Retroactive changes | R344: Changing past projects | S344: Distrust | T344: No | U344: No — included in base price | V344: No

Sheet Contribution Library
A1: ID | B1: Category | C1: Task | D1: Description | E1: Default Points | F1: Complexity | G1: Estimated Effort | H1: Evidence | I1: Client Approval | J1: Mandatory/Optional/Conditional | K1: Typical Owner | L1: Dependencies | M1: Billable? | N1: Post-launch?
A2: A-01 | B2: Lead Generation | C2: Build prospect list | D2: List local businesses in a target niche/area with no site, an outdated site, or a site that fails mobile/speed checks; record name, contact, source, current URL | E2: 2 | F2: Low | G2: 1–3 h per 20 leads | H2: CRM/sheet export with dates | I2: No | J2: [RECOMMENDED] | K2: Sales | L2: — | M2: No — included in base price | N2: No
A3: A-02 | B3: Lead Generation | C3: Prospect mini-audit | D3: Quick audit of prospect's site, Google Business Profile, socials: mobile view, speed, HTTPS, broken contact info; 3–5 concrete findings | E3: 1 | F3: Low | G3: 0.5–1 h | H3: Audit doc/screenshots linked to lead | I3: No | J3: [OPTIONAL] | K3: Sales | L3: A-01 | M3: No — included in base price | N3: No
A4: A-03 | B4: Lead Generation | C4: Log lead with source and status | D4: Create lead record: business, contact person, phone/email, source, date, next action, status | E4: 1 | F4: Low | G4: 5–10 min | H4: CRM/app entry with timestamp | I4: No | J4: [MUST HAVE] | K4: Either | L4: — | M4: No — included in base price | N4: No
A5: A-04 | B5: Lead Generation | C5: Referral and partner outreach | D5: Ask past clients, CAs, printers, photographers, marketers for referrals; track referrer | E5: 2 | F5: Low | G5: 1–2 h/month | H5: Messages/call notes | I5: No | J5: [RECOMMENDED] | K5: Sales | L5: — | M5: No — included in base price | N5: No
A6: B-01 | B6: Client Outreach | C6: Write personalised outreach message | D6: Draft first message referencing audit findings and a clear next step (15-min call) | E6: 1 | F6: Low | G6: 15–30 min | H6: Sent message copy/screenshot | I6: No | J6: [RECOMMENDED] | K6: Sales | L6: A-02, A-03 | M6: No — included in base price | N6: No
A7: B-02 | B7: Client Outreach | C7: First contact and log outcome | D7: Call/visit/message; record date, channel, who, outcome, next step | E7: 1 | F7: Low | G7: 10–30 min | H7: Call log/meeting note | I7: No | J7: [MUST HAVE] | K7: Sales | L7: B-01 | M7: No — included in base price | N7: No
A8: B-03 | B8: Client Outreach | C8: Follow-up sequence | D8: Up to 2–3 spaced follow-ups with added value (example, audit point); stop after no response | E8: 1 | F8: Low | G8: 10 min each | H8: Message copies with dates | I8: No | J8: [RECOMMENDED] | K8: Sales | L8: B-02 | M8: No — included in base price | N8: No
A9: B-04 | B9: Client Outreach | C9: Share portfolio and case studies | D9: Send 2–3 relevant samples with outcome, scope and price band | E9: 1 | F9: Low | G9: 15–30 min | H9: Sent link record | I9: No | J9: [RECOMMENDED] | K9: Sales | L9: B-02 | M9: No — included in base price | N9: No
A10: C-01 | B10: Sales | C10: Qualification call | D10: 15–30 min call covering need, decision-maker, budget range, timeline, existing assets | E10: 1 | F10: Low | G10: 0.5–1 h | H10: Call note in app | I10: No | J10: [MUST HAVE] | K10: Sales | L10: B-02 | M10: No — included in base price | N10: No
A11: C-02 | B11: Sales | C11: Go/no-go decision | D11: Decide proceed or decline using checklist: budget fit, timeline realism, legal business, red flags; record reason | E11: 1 | F11: Low | G11: 10–20 min | H11: Decision entry with reason | I11: No | J11: [RECOMMENDED] | K11: Either | L11: C-01 | M11: No — included in base price | N11: No
A12: C-03 | B12: Sales | C12: Sales meeting or demo | D12: Present approach, process, timeline, samples; explain payment terms and ownership model upfront | E12: 2 | F12: Medium | G12: 1–2 h incl. prep | H12: Meeting record + attendee list | I12: No | J12: [RECOMMENDED] | K12: Sales | L12: C-02 | M12: No — included in base price | N12: No
A13: C-04 | B13: Sales | C13: Pricing negotiation | D13: Negotiate by adjusting scope, not just price; record every concession in writing | E13: 2 | F13: Medium | G13: 0.5–2 h | H13: Email/notes, version history | I13: Yes | J13: [RECOMMENDED] | K13: Sales | L13: G-03 | M13: No — included in base price | N13: No
... A344: BO-02 | B344: Partner Governance (added) | C344: Points calibration review | D344: Quarterly compare points vs actual effort across projects; adjust defaults going forward only | E344: 1 | F344: Low | G344: 1–2 h | H344: Changelog of defaults | I344: No | J344: [RECOMMENDED] | K344: Either (both) | L344: BJ-01 | M344: No — included in base price | N344: No

Sheet Category Summary
A1: Code | B1: Category | C1: Tasks | D1: MUST HAVE tasks | E1: Default points (all) | F1: Points (MUST HAVE only) | G1: Share of all points
A2: A | B2: Lead Generation | C2: =COUNTIF('Task Library'!$B$2:$B$344,A2) -> 4 | D2: =COUNTIFS('Task Library'!$B$2:$B$344,A2,'Task Library'!$M$2:$M$344,"[MUST HAVE]") -> 1 | E2: =SUMIF('Task Library'!$B$2:$B$344,A2,'Task Library'!$P$2:$P$344) -> 6 | F2: =SUMIFS('Task Library'!$P$2:$P$344,'Task Library'!$B$2:$B$344,A2,'Task Library'!$M$2:$M$344,"[MUST HAVE]") -> 1 | G2: =IF($E$69=0,0,E2/$E$69) -> 0.0089552239
A3: B | B3: Client Outreach | C3: =COUNTIF('Task Library'!$B$2:$B$344,A3) -> 4 | D3: =COUNTIFS('Task Library'!$B$2:$B$344,A3,'Task Library'!$M$2:$M$344,"[MUST HAVE]") -> 1 | E3: =SUMIF('Task Library'!$B$2:$B$344,A3,'Task Library'!$P$2:$P$344) -> 4 | F3: =SUMIFS('Task Library'!$P$2:$P$344,'Task Library'!$B$2:$B$344,A3,'Task Library'!$M$2:$M$344,"[MUST HAVE]") -> 1 | G3: =IF($E$69=0,0,E3/$E$69) -> 0.0059701493
A4: C | B4: Sales | C4: =COUNTIF('Task Library'!$B$2:$B$344,A4) -> 5 | D4: =COUNTIFS('Task Library'!$B$2:$B$344,A4,'Task Library'!$M$2:$M$344,"[MUST HAVE]") -> 1 | E4: =SUMIF('Task Library'!$B$2:$B$344,A4,'Task Library'!$P$2:$P$344) -> 7 | F4: =SUMIFS('Task Library'!$P$2:$P$344,'Task Library'!$B$2:$B$344,A4,'Task Library'!$M$2:$M$344,"[MUST HAVE]") -> 1 | G4: =IF($E$69=0,0,E4/$E$69) -> 0.010447761
A5: D | B5: Discovery | C5: =COUNTIF('Task Library'!$B$2:$B$344,A5) -> 5 | D5: =COUNTIFS('Task Library'!$B$2:$B$344,A5,'Task Library'!$M$2:$M$344,"[MUST HAVE]") -> 5 | E5: =SUMIF('Task Library'!$B$2:$B$344,A5,'Task Library'!$P$2:$P$344) -> 8 | F5: =SUMIFS('Task Library'!$P$2:$P$344,'Task Library'!$B$2:$B$344,A5,'Task Library'!$M$2:$M$344,"[MUST HAVE]") -> 8 | G5: =IF($E$69=0,0,E5/$E$69) -> 0.011940299
A6: E | B6: Requirements Gathering | C6: =COUNTIF('Task Library'!$B$2:$B$344,A6) -> 7 | D6: =COUNTIFS('Task Library'!$B$2:$B$344,A6,'Task Library'!$M$2:$M$344,"[MUST HAVE]") -> 6 | E6: =SUMIF('Task Library'!$B$2:$B$344,A6,'Task Library'!$P$2:$P$344) -> 10 | F6: =SUMIFS('Task Library'!$P$2:$P$344,'Task Library'!$B$2:$B$344,A6,'Task Library'!$M$2:$M$344,"[MUST HAVE]") -> 9 | G6: =IF($E$69=0,0,E6/$E$69) -> 0.014925373
A7: F | B7: Scope Definition | C7: =COUNTIF('Task Library'!$B$2:$B$344,A7) -> 5 | D7: =COUNTIFS('Task Library'!$B$2:$B$344,A7,'Task Library'!$M$2:$M$344,"[MUST HAVE]") -> 5 | E7: =SUMIF('Task Library'!$B$2:$B$344,A7,'Task Library'!$P$2:$P$344) -> 6 | F7: =SUMIFS('Task Library'!$P$2:$P$344,'Task Library'!$B$2:$B$344,A7,'Task Library'!$M$2:$M$344,"[MUST HAVE]") -> 6 | G7: =IF($E$69=0,0,E7/$E$69) -> 0.0089552239
A8: G | B8: Proposal/Quotation | C8: =COUNTIF('Task Library'!$B$2:$B$344,A8) -> 6 | D8: =COUNTIFS('Task Library'!$B$2:$B$344,A8,'Task Library'!$M$2:$M$344,"[MUST HAVE]") -> 3 | E8: =SUMIF('Task Library'!$B$2:$B$344,A8,'Task Library'!$P$2:$P$344) -> 11 | F8: =SUMIFS('Task Library'!$P$2:$P$344,'Task Library'!$B$2:$B$344,A8,'Task Library'!$M$2:$M$344,"[MUST HAVE]") -> 8 | G8: =IF($E$69=0,0,E8/$E$69) -> 0.01641791
A9: H | B9: Contract/Agreement | C9: =COUNTIF('Task Library'!$B$2:$B$344,A9) -> 6 | D9: =COUNTIFS('Task Library'!$B$2:$B$344,A9,'Task Library'!$M$2:$M$344,"[MUST HAVE]") -> 4 | E9: =SUMIF('Task Library'!$B$2:$B$344,A9,'Task Library'!$P$2:$P$344) -> 7 | F9: =SUMIFS('Task Library'!$P$2:$P$344,'Task Library'!$B$2:$B$344,A9,'Task Library'!$M$2:$M$344,"[MUST HAVE]") -> 5 | G9: =IF($E$69=0,0,E9/$E$69) -> 0.010447761
A10: I | B10: Payment/Invoice | C10: =COUNTIF('Task Library'!$B$2:$B$344,A10) -> 6 | D10: =COUNTIFS('Task Library'!$B$2:$B$344,A10,'Task Library'!$M$2:$M$344,"[MUST HAVE]") -> 5 | E10: =SUMIF('Task Library'!$B$2:$B$344,A10,'Task Library'!$P$2:$P$344) -> 6 | F10: =SUMIFS('Task Library'!$P$2:$P$344,'Task Library'!$B$2:$B$344,A10,'Task Library'!$M$2:$M$344,"[MUST HAVE]") -> 5 | G10: =IF($E$69=0,0,E10/$E$69) -> 0.0089552239
A11: J | B11: Project Setup | C11: =COUNTIF('Task Library'!$B$2:$B$344,A11) -> 8 | D11: =COUNTIFS('Task Library'!$B$2:$B$344,A11,'Task Library'!$M$2:$M$344,"[MUST HAVE]") -> 8 | E11: =SUMIF('Task Library'!$B$2:$B$344,A11,'Task Library'!$P$2:$P$344) -> 11 | F11: =SUMIFS('Task Library'!$P$2:$P$344,'Task Library'!$B$2:$B$344,A11,'Task Library'!$M$2:$M$344,"[MUST HAVE]") -> 11 | G11: =IF($E$69=0,0,E11/$E$69) -> 0.01641791
A12: K | B12: Client Communication | C12: =COUNTIF('Task Library'!$B$2:$B$344,A12) -> 5 | D12: =COUNTIFS('Task Library'!$B$2:$B$344,A12,'Task Library'!$M$2:$M$344,"[MUST HAVE]") -> 1 | E12: =SUMIF('Task Library'!$B$2:$B$344,A12,'Task Library'!$P$2:$P$344) -> 6 | F12: =SUMIFS('Task Library'!$P$2:$P$344,'Task Library'!$B$2:$B$344,A12,'Task Library'!$M$2:$M$344,"[MUST HAVE]") -> 1 | G12: =IF($E$69=0,0,E12/$E$69) -> 0.0089552239
A13: L | B13: Research | C13: =COUNTIF('Task Library'!$B$2:$B$344,A13) -> 5 | D13: =COUNTIFS('Task Library'!$B$2:$B$344,A13,'Task Library'!$M$2:$M$344,"[MUST HAVE]") -> 2 | E13: =SUMIF('Task Library'!$B$2:$B$344,A13,'Task Library'!$P$2:$P$344) -> 11 | F13: =SUMIFS('Task Library'!$P$2:$P$344,'Task Library'!$B$2:$B$344,A13,'Task Library'!$M$2:$M$344,"[MUST HAVE]") -> 3 | G13: =IF($E$69=0,0,E13/$E$69) -> 0.01641791
... A68: BO | B68: Partner Governance (added) | C68: =COUNTIF('Task Library'!$B$2:$B$344,A68) -> 2 | D68: =COUNTIFS('Task Library'!$B$2:$B$344,A68,'Task Library'!$M$2:$M$344,"[MUST HAVE]") -> 0 | E68: =SUMIF('Task Library'!$B$2:$B$344,A68,'Task Library'!$P$2:$P$344) -> 2 | F68: =SUMIFS('Task Library'!$P$2:$P$344,'Task Library'!$B$2:$B$344,A68,'Task Library'!$M$2:$M$344,"[MUST HAVE]") -> 0 | G68: =IF($E$69=0,0,E68/$E$69) -> 0.0029850746
B69: TOTAL | C69: =SUM(C2:C68) -> 343 | D69: =SUM(D2:D68) -> 179 | E69: =SUM(E2:E68) -> 670 | F69: =SUM(F2:F68) -> 277 | G69: =SUM(G2:G68) -> 1
